<?xml version="1.0" encoding="utf-8" ?>
<dwsync>
<file name="bgshade.jpg" server="ghisfastners.com//public_html/" local="130266421562518273" remote="130319049000000000" Dst="0" />
<file name="shade.png" server="ghisfastners.com//public_html/" local="129216713220000000" remote="130319049000000000" Dst="0" />
<file name="logo.png" server="ghisfastners.com//public_html/" local="130257106819646200" remote="130319049600000000" Dst="0" />
<file name="callus.png" server="ghisfastners.com//public_html/" local="130317273104597777" remote="130319049600000000" Dst="0" />
<file name="slide3.jpg" server="ghisfastners.com//public_html/" local="130261203685729873" remote="130319104800000000" Dst="0" />
<file name="slide2.jpg" server="ghisfastners.com//public_html/" local="130261159914286290" remote="130319104800000000" Dst="0" />
<file name="slide1.jpg" server="ghisfastners.com//public_html/" local="130261160056124402" remote="130319104800000000" Dst="0" />
<file name="slide4.jpg" server="ghisfastners.com//public_html/" local="130261214426154190" remote="130319104800000000" Dst="0" />
<file name="slide5.jpg" server="ghisfastners.com//public_html/" local="130261215006607390" remote="130319105400000000" Dst="0" />
<file name="slide6.jpg" server="ghisfastners.com//public_html/" local="130261215378798678" remote="130319105400000000" Dst="0" />
<file name="bgshade.jpg" server="D:/wamp/www/generalHardware/" local="130266421562518273" remote="130266421560000000" Dst="0" />
<file name="shade.png" server="D:/wamp/www/generalHardware/" local="129216713220000000" remote="129216713220000000" Dst="0" />
<file name="logo.png" server="D:/wamp/www/generalHardware/" local="130257106819646200" remote="130257106810000000" Dst="0" />
<file name="callus.png" server="D:/wamp/www/generalHardware/" local="130317273104597777" remote="130317273100000000" Dst="0" />
<file name="aboutus.jpg" server="D:/wamp/www/generalHardware/" local="130319187479158698" remote="130319187470000000" Dst="0" />
</dwsync>